timexwiz/__init__.py
timexwiz/measure_timer.py
timexwiz/predict.py
timexwiz-1.0.1.dist-info/LICENSE
timexwiz-1.0.1.dist-info/METADATA
timexwiz-1.0.1.dist-info/WHEEL
timexwiz-1.0.1.dist-info/top_level.txt
timexwiz-1.0.1.dist-info/RECORD
