Metadata-Version: 2.1
Name: timexwiz
Version: 1.0.1
Summary: Timexwiz is a simple Python library for time measure, benchmarking and algorithm comparisons.
Home-page: https://github.com/UncleDrema/timexwiz
Author: UncleDrema
Author-email: missl.wipiece@gmail.com
License: MIT
Keywords: measure,benchmark,time,library,Python
Classifier: Development Status :: 5 - Production/Stable
Classifier: Intended Audience :: Developers
Classifier: License :: OSI Approved :: MIT License
Classifier: Programming Language :: Python
Classifier: Programming Language :: Python :: 3
Classifier: Programming Language :: Python :: 3.6
Classifier: Programming Language :: Python :: 3.7
Classifier: Programming Language :: Python :: 3.8
Classifier: Programming Language :: Python :: 3.9
Classifier: Programming Language :: Python :: 3.10
Classifier: Programming Language :: Python :: 3.11
License-File: LICENSE
